pgsrip/__init__.py
pgsrip/__main__.py
pgsrip/api.py
pgsrip/cli.py
pgsrip/core.py
pgsrip/media.py
pgsrip/media_path.py
pgsrip/mkv.py
pgsrip/options.py
pgsrip/pgs.py
pgsrip/ripper.py
pgsrip/sup.py
pgsrip/tsv.py
pgsrip/utils.py
pgsrip-0.1.11.dist-info/LICENSE
pgsrip-0.1.11.dist-info/METADATA
pgsrip-0.1.11.dist-info/WHEEL
pgsrip-0.1.11.dist-info/entry_points.txt
pgsrip-0.1.11.dist-info/RECORD
