Metadata-Version: 2.1
Name: pgsrip
Version: 0.1.11
Summary: Rip your PGS subtitles
Home-page: https://github.com/ratoaq2/pgsrip
License: MIT
Keywords: video,mkv,subtitles,rip,srt,pgs,sup,sub,metadata,movie,episode,tv,shows,series
Author: Rato
Requires-Python: >=3.9.0,<4.0.0
Classifier: Development Status :: 5 - Production/Stable
Classifier: Intended Audience :: Developers
Classifier: License :: OSI Approved :: Apache Software License
Classifier: License :: OSI Approved :: MIT License
Classifier: Operating System :: OS Independent
Classifier: Programming Language :: Python
Classifier: Programming Language :: Python :: 3
Classifier: Programming Language :: Python :: 3.9
Classifier: Programming Language :: Python :: 3.10
Classifier: Programming Language :: Python :: 3.11
Classifier: Programming Language :: Python :: 3.12
Classifier: Programming Language :: Python :: 3 :: Only
Classifier: Topic :: Multimedia :: Video
Classifier: Topic :: Software Development :: Libraries :: Python Modules
Requires-Dist: babelfish (>=0.6.1,<0.7.0)
Requires-Dist: cleanit (>=0.4.8,<0.5.0)
Requires-Dist: click (>=8.1.3,<9.0.0)
Requires-Dist: numpy (>=2.0.0,<3.0.0)
Requires-Dist: opencv-python (>=4.7.0,<5.0.0)
Requires-Dist: pysrt (>=1.1.2,<2.0.0)
Requires-Dist: pytesseract (>=0.3.10,<0.4.0)
Requires-Dist: setuptools (>=70.1.0,<71.0.0)
Requires-Dist: trakit (>=0.2.2,<0.3.0)
Project-URL: Repository, https://github.com/ratoaq2/pgsrip
